MANIFEST.in
setup.py
src/django_webid/__init__.py
src/django_webid/auth/__init__.py
src/django_webid/auth/backends.py
src/django_webid/auth/decorators.py
src/django_webid/auth/middleware.py
src/django_webid/auth/models.py
src/django_webid/auth/util.py
src/django_webid/auth/tests/__init__.py
src/django_webid/auth/tests/sample.py
src/django_webid_auth.egg-info/PKG-INFO
src/django_webid_auth.egg-info/SOURCES.txt
src/django_webid_auth.egg-info/dependency_links.txt
src/django_webid_auth.egg-info/namespace_packages.txt
src/django_webid_auth.egg-info/not-zip-safe
src/django_webid_auth.egg-info/requires.txt
src/django_webid_auth.egg-info/top_level.txt