Metadata-Version: 1.1
Name: django-webid-auth
Version: 0.2
Summary: A django app to enable WebID authentication.
Home-page: UNKNOWN
Author: Ben Carrillo
Author-email: bennomadic@gmail.com
License: UNKNOWN
Download-URL: https://github.com/bennomadic/django-webid-auth.git
Keywords: foaf,ssl,webid,x509,certificate,client certificate,authentication,authorization,django
Platform: UNKNOWN
Classifier: Development Status :: 3 - Alpha
Classifier: Environment :: Web Environment
Classifier: Intended Audience :: Developers
Classifier: License :: OSI Approved :: GNU General Public License (GPL)
Classifier: Operating System :: OS Independent
Classifier: Programming Language :: Python
Classifier: Programming Language :: JavaScript
Classifier: Framework :: Django
Classifier: Topic :: Internet :: WWW/HTTP
Classifier: Topic :: Software Development :: Libraries :: Python Modules
